utility_api/__init__.py
utility_api/models/endpoints/authorization.py
utility_api/models/endpoints/bill.py
utility_api/models/endpoints/form.py
utility_api/models/endpoints/interval.py
utility_api/models/endpoints/meter.py
utility_api/models/object_types/base_enum.py
utility_api/models/object_types/bill_types.py
utility_api/models/object_types/general_types.py
utility_api/models/object_types/interval_types.py
utility_api/models/object_types/meter_types.py
utility_api/models/object_types/test_scenario.py
utility_api/service.py
utility_api-0.2.3.dist-info/METADATA
utility_api-0.2.3.dist-info/WHEEL
utility_api-0.2.3.dist-info/RECORD
