Metadata-Version: 2.1
Name: utility-api
Version: 0.2.3
Summary: An interface for interacting with Utility API
Author: Gabrielle Anne Sblendorio
Author-email: glsblendorio@gmail.com
Requires-Python: >=3.8.1,<3.13
Classifier: Programming Language :: Python :: 3
Classifier: Programming Language :: Python :: 3.9
Classifier: Programming Language :: Python :: 3.10
Classifier: Programming Language :: Python :: 3.11
Classifier: Programming Language :: Python :: 3.12
Requires-Dist: dataclasses-json (>=0.5.14,<0.6.0)
Requires-Dist: parsy (>=2.1,<3.0)
Requires-Dist: python-dotenv (>=1.0.0,<2.0.0)
Requires-Dist: requests (>=2.31.0,<3.0.0)
